rofi_spotify/__init__.py
rofi_spotify/config.py
rofi_spotify/rofi_spotify.py
rofi_spotify-0.0.1.data/scripts/rofi-spotify
rofi_spotify-0.0.1.dist-info/LICENSE
rofi_spotify-0.0.1.dist-info/METADATA
rofi_spotify-0.0.1.dist-info/WHEEL
rofi_spotify-0.0.1.dist-info/top_level.txt
rofi_spotify-0.0.1.dist-info/RECORD
